locuaz/__init__.py
locuaz/abstractmutationgenerator.py
locuaz/abstractpruner.py
locuaz/abstractscorer.py
locuaz/amberutils.py
locuaz/aminoacidselector.py
locuaz/autodockvina.py
locuaz/bach.py
locuaz/basemutator.py
locuaz/basestatistic.py
locuaz/bluues.py
locuaz/bluuesbmf.py
locuaz/cli.py
locuaz/complex.py
locuaz/epochinitializer.py
locuaz/evoef2.py
locuaz/fileutils.py
locuaz/fixbox.py
locuaz/gmxmmpbsa.py
locuaz/gromacsutils.py
locuaz/haddock.py
locuaz/interface.py
locuaz/molecules.py
locuaz/moleculesutils.py
locuaz/molutils.py
locuaz/mutation.py
locuaz/mutationcreation.py
locuaz/mutationgenerators.py
locuaz/mutatorbiobb.py
locuaz/mutatordlp.py
locuaz/mutatordlpr.py
locuaz/mutatorevoef2.py
locuaz/mutators.py
locuaz/piepisa.py
locuaz/pisa.py
locuaz/pools.py
locuaz/primitives.py
locuaz/projectutils.py
locuaz/protocol.py
locuaz/pruner.py
locuaz/prunerconsensus.py
locuaz/prunermetropolis.py
locuaz/prunerroundrobin.py
locuaz/pruners.py
locuaz/pruning.py
locuaz/reis_barletta_cdr.csv
locuaz/reis_barletta_full.csv
locuaz/rosetta.py
locuaz/run.py
locuaz/runutils.py
locuaz/schema.yaml
locuaz/scorers.py
locuaz/scoring.py
locuaz/siteselector.py
locuaz/spm4.py
locuaz/spm4i.py
locuaz/spm4mmpbsa.py
locuaz/statisticcmdistance.py
locuaz/statisticinterface.py
locuaz/statistics.py
locuaz/uniform.csv
locuaz/utils_scoring.py
locuaz/validatore.py
locuaz/DLPacker/__init__.py
locuaz/DLPacker/charges.rtp
locuaz/DLPacker/dlpacker.py
locuaz/DLPacker/library.npz
locuaz/DLPacker/utils.py
locuaz/sample_bin/aux_scripts/reorder_pdb.py
locuaz/sample_bin/dlpacker/charges.rtp
locuaz/sample_bin/dlpacker/library.npz
locuaz/sample_bin/gmxmmpbsa/gmxmmpbsa
locuaz/sample_bin/haddock/template_scoring.inp
locuaz-0.7.5.4.dist-info/LICENSE.rst
locuaz-0.7.5.4.dist-info/METADATA
locuaz-0.7.5.4.dist-info/WHEEL
locuaz-0.7.5.4.dist-info/entry_points.txt
locuaz-0.7.5.4.dist-info/top_level.txt
locuaz-0.7.5.4.dist-info/RECORD
