Metadata-Version: 2.1
Name: locuaz
Version: 0.7.5.4
Summary: Antibody optimization protocol
Author: Patricio Barletta
Author-email: pbarletta@gmail.com
Keywords: molecular,dynamics,antibody,antibodies
Requires-Python: >=3.10
License-File: LICENSE.rst
Requires-Dist: py
Requires-Dist: scipy
Requires-Dist: numpy <2.0.0,>=1.21.0
Requires-Dist: attrs
Requires-Dist: chemfiles
Requires-Dist: mdanalysis >=2.6.0
Requires-Dist: networkx
Requires-Dist: biobb-common
Requires-Dist: biobb-analysis
Requires-Dist: biobb-model
Requires-Dist: biobb-io
Requires-Dist: biobb-gromacs
Requires-Dist: pdb2pqr
Requires-Dist: gmx-mmpbsa ==1.6.1
Requires-Dist: tqdm
Requires-Dist: freesasa
Requires-Dist: pytest
Requires-Dist: cerberus
Requires-Dist: Deprecated
Provides-Extra: docs
Requires-Dist: sphinx ; extra == 'docs'
Requires-Dist: sphinx-rtd-theme ; extra == 'docs'
